{
  "platform": "nextjs",
  "code": {
    "lang": "ts",
    "scheme": "blackbox",
    "reactRuntime": "classic"
  },
  "style": {
    "scheme": "css-modules",
    "defaultStyleCssFilePath": "plasmic/plasmic__default_style.css"
  },
  "images": {
    "scheme": "public-files",
    "publicDir": "../public",
    "publicUrlPrefix": "/"
  },
  "tokens": {
    "scheme": "theo",
    "tokensFilePath": "plasmic-tokens.theo.json"
  },
  "srcDir": "components",
  "defaultPlasmicDir": "./plasmic",
  "projects": [
    {
      "projectId": "oNeqSCDLQSb2sSwYyePyFD",
      "projectApiToken": "qEWGSeqsMS2krNF6yk2dzYjtsatALOhGdUMdbCSxl7eay1CkwmJV5jXnVkFPBMBIWC1K8ZI0of2DG8PHB41Fg",
      "projectName": "Website starter",
      "version": "latest",
      "cssFilePath": "plasmic/website_starter/plasmic_website_starter.module.css",
      "components": [
        {
          "id": "_nmV0ZctZM",
          "name": "Homepage",
          "type": "managed",
          "projectId": "oNeqSCDLQSb2sSwYyePyFD",
          "renderModuleFilePath": "plasmic/website_starter/PlasmicHomepage.tsx",
          "importSpec": {
            "modulePath": "../pages/index.tsx"
          },
          "cssFilePath": "plasmic/website_starter/PlasmicHomepage.module.css",
          "scheme": "blackbox",
          "componentType": "page"
        },
        {
          "id": "XChw7lJY185",
          "name": "TextInput",
          "type": "managed",
          "projectId": "oNeqSCDLQSb2sSwYyePyFD",
          "renderModuleFilePath": "plasmic/website_starter/PlasmicTextInput.tsx",
          "importSpec": {
            "modulePath": "TextInput.tsx"
          },
          "cssFilePath": "plasmic/website_starter/PlasmicTextInput.module.css",
          "scheme": "blackbox",
          "componentType": "component",
          "plumeType": "text-input"
        },
        {
          "id": "zHFWxkOhsLH",
          "name": "Button",
          "type": "managed",
          "projectId": "oNeqSCDLQSb2sSwYyePyFD",
          "renderModuleFilePath": "plasmic/website_starter/PlasmicButton.tsx",
          "importSpec": {
            "modulePath": "Button.tsx"
          },
          "cssFilePath": "plasmic/website_starter/PlasmicButton.module.css",
          "scheme": "blackbox",
          "componentType": "component",
          "plumeType": "button"
        }
      ],
      "icons": [
        {
          "id": "qqzMjO1S48d",
          "name": "SearchsvgIcon",
          "moduleFilePath": "plasmic/website_starter/icons/PlasmicIcon__Searchsvg.tsx"
        },
        {
          "id": "RTHebNJg3nh",
          "name": "ChecksvgIcon",
          "moduleFilePath": "plasmic/website_starter/icons/PlasmicIcon__Checksvg.tsx"
        },
        {
          "id": "osJOkC_Rpat",
          "name": "IconIcon",
          "moduleFilePath": "plasmic/website_starter/icons/PlasmicIcon__Icon.tsx"
        }
      ],
      "images": [],
      "indirect": false,
      "globalContextsFilePath": "",
      "codeComponents": [
        {
          "id": "_NmiESAsU5n",
          "name": "PlasmicHead",
          "displayName": "hostless-plasmic-head",
          "componentImportPath": "@plasmicapp/react-web"
        },
        {
          "id": "8qE3sPMjv88",
          "name": "Fetcher",
          "displayName": "plasmic-data-source-fetcher",
          "componentImportPath": "@plasmicapp/react-web/lib/data-sources"
        }
      ]
    }
  ],
  "globalVariants": {
    "variantGroups": [
      {
        "id": "E8dTTQoIxWr",
        "name": "Screen",
        "projectId": "oNeqSCDLQSb2sSwYyePyFD",
        "contextFilePath": "plasmic/website_starter/PlasmicGlobalVariant__Screen.tsx"
      }
    ]
  },
  "wrapPagesWithGlobalContexts": true,
  "nextjsConfig": {
    "pagesDir": "../pages"
  },
  "cliVersion": "0.1.304",
  "$schema": "https://unpkg.com/@plasmicapp/cli@0.1.304/dist/plasmic.schema.json"
}
